<?xml version="1.0"?>
<playlist name="_TEN">
	<song file="session/lostman.xml"/>
	<song class="FreshWidow"/>
	<song class="OKeymickey"/>
	<song class="Punkrocker"/>
	<song class="SheLost"/>
	<song file="session/sunlight.xml"/>
	<song file="session/anemickover3.xml"/>
	<song file="session/b17.xml"/>
	<song file="session/ahardplace_eng.xml"/>
	<song file="session/antarctic.xml"/>
	<song file="session/songzero.xml"/>
	<song file="session/charlottesometimes.xml"/>
	<song file="session/slowlybittingU.xml"/>
	<song file="session/flag.xml"/>
	<song file="session/loveedn.xml"/>
</playlist>